{
    "questions": {
        "سحرخیزی":{   
            "topic_image" : "https://cdn.dribbble.com/users/5029209/screenshots/14400954/media/6ffd4ea2bb76da2380cd6ff37c97bf3e.png?compress=1&resize=1000x750",
            "secound_questions" : {
                "title": "",
                "options": {
                    "1":"",
                    "2":"",
                    "3":""
                }
            } 
        },

        "قانون جذب":{ 
            "topic_image" : "https://cdn.dribbble.com/users/518045/screenshots/14127393/media/e21fe0b76fd93b87cbee371108503b99.png?compress=1&resize=1000x750",
            "secound_questions" : {
                "title": "",
                "options": {
                    "1":"https://cdn.dribbble.com/users/440670/screenshots/15244462/media/b233e4aae0e0ce91c368d86454ac63f4.jpg?compress=1&resize=1000x750",
                    "2":"",
                    "3":""
                }
            } 
        },
        
        "هوش مالی":{  
            "topic_image" : "https://cdn.dribbble.com/users/1626229/screenshots/10802257/media/75691f6399f58e18a48ca28e15abd756.jpg?compress=1&resize=1000x750",
            "secound_questions" : {
                "title": "",
                "options": {
                    "1":"",
                    "2":"",
                    "3":""
                }
            } 
        },
        
        "کارافرینی": {    
            "topic_image" : "https://cdn.dribbble.com/users/1626229/screenshots/15021591/media/cebadbe7c5df1565621cf205c17483ad.jpg?compress=1&resize=1000x750",
            "secound_questions" : {
                "title": "",
                "options": {
                    "1":"",
                    "2":"",
                    "3":""
                }
            } 
        },
        
        "برندسازی":{      
            "topic_image" : "https://cdn.dribbble.com/users/2394977/screenshots/14645014/media/14d52d6a640b7aec85be9aeae29f0a56.jpg?compress=1&resize=1000x750",
            "secound_questions" : {
                "title": "",
                "options": {
                    "1":"",
                    "2":"",
                    "3":""
                }
            } 
        },
        
        "برنامه ریزی": {
            "topic_image" : "https://cdn.dribbble.com/users/1137072/screenshots/11957131/media/8ba20e5cc46f423d05fb8907ddd7dcd0.png?compress=1&resize=1000x750",
            "secound_questions" : {
                "title": "",
                "options": {
                    "1":"",
                    "2":"",
                    "3":""
                }
            }    
        }
    }

}